ioka_lib/__init__.py
ioka_lib/base.py
ioka_lib/customers.py
ioka_lib/dashboard.py
ioka_lib/orders.py
ioka_lib/payments.py
ioka_lib/webhooks.py
tests/__init__.py
tests/test_orders.py
tests/test_payments.py
ioka_lib-0.1.dist-info/METADATA
ioka_lib-0.1.dist-info/WHEEL
ioka_lib-0.1.dist-info/top_level.txt
ioka_lib-0.1.dist-info/RECORD
